Metadata-Version: 2.1
Name: shapflex
Version: 0.0.2
Summary: A python version of R package for computing asymmetric Shapley values to assess causality in any trained machine learning model
Home-page: https://github.com/gregory-ch/shapflex
Author: Gregory Ch
Author-email: cubekot@gmail.com
License: MIT license
Keywords: shapflex
Platform: UNKNOWN
Classifier: Development Status :: 2 - Pre-Alpha
Classifier: Intended Audience :: Developers
Classifier: License :: OSI Approved :: MIT License
Classifier: Natural Language :: English
Classifier: Programming Language :: Python :: 3
Classifier: Programming Language :: Python :: 3.7
Classifier: Programming Language :: Python :: 3.8
Classifier: Programming Language :: Python :: 3.9
Requires-Python: >=3.7
License-File: LICENSE
